dopys/__init__.py
dopys-0.1.0.dist-info/LICENSE
dopys-0.1.0.dist-info/METADATA
dopys-0.1.0.dist-info/WHEEL
dopys-0.1.0.dist-info/RECORD
