Metadata-Version: 2.1
Name: dopys
Version: 0.1.0
Summary: Dopys is a note taking app
License: GPLv3
Author: Max Ligus
Author-email: max.ligus@gmail.com
Requires-Python: >=3.10,<4.0
Classifier: License :: Other/Proprietary License
Classifier: Programming Language :: Python :: 3
Classifier: Programming Language :: Python :: 3.10
Classifier: Programming Language :: Python :: 3.11
